konfigmapedit/__init__.py
konfigmapedit/__main__.py
konfigmapedit/app_module.py
konfigmapedit-0.1.0.dist-info/LICENSE.txt
konfigmapedit-0.1.0.dist-info/METADATA
konfigmapedit-0.1.0.dist-info/WHEEL
konfigmapedit-0.1.0.dist-info/entry_points.txt
konfigmapedit-0.1.0.dist-info/top_level.txt
konfigmapedit-0.1.0.dist-info/RECORD
