Metadata-Version: 2.1
Name: konfigmapedit
Version: 0.1.0
Summary: Edit multi-file Kubernetes configmaps by downloading them into a folder, let you edit in an interactive shell and uploads them after.
Author-email: Armin Zentai <armin@zentai.name>
License: MIT License
Keywords: kubernetes,configmap,edit,editor,interactive
Requires-Python: >=3.6
License-File: LICENSE.txt
Requires-Dist: kubernetes (>=26.0.0)
Provides-Extra: dev
Requires-Dist: pip-tools ; extra == 'dev'
